odoo/addons/mrp_bom_location/README.rst
odoo/addons/mrp_bom_location/__init__.py
odoo/addons/mrp_bom_location/__manifest__.py
odoo/addons/mrp_bom_location/i18n/de.po
odoo/addons/mrp_bom_location/i18n/es.po
odoo/addons/mrp_bom_location/i18n/hr.po
odoo/addons/mrp_bom_location/i18n/it.po
odoo/addons/mrp_bom_location/i18n/mrp_bom_location.pot
odoo/addons/mrp_bom_location/i18n/pt_BR.po
odoo/addons/mrp_bom_location/i18n/tr.po
odoo/addons/mrp_bom_location/models/__init__.py
odoo/addons/mrp_bom_location/models/mrp_bom.py
odoo/addons/mrp_bom_location/readme/CONTRIBUTORS.md
odoo/addons/mrp_bom_location/readme/CREDITS.md
odoo/addons/mrp_bom_location/readme/DESCRIPTION.md
odoo/addons/mrp_bom_location/readme/USAGE.md
odoo/addons/mrp_bom_location/report/__init__.py
odoo/addons/mrp_bom_location/report/bom_structure.py
odoo/addons/mrp_bom_location/static/description/icon.png
odoo/addons/mrp_bom_location/static/description/index.html
odoo/addons/mrp_bom_location/static/src/xml/mrp_bom_overview_location.xml
odoo/addons/mrp_bom_location/tests/__init__.py
odoo/addons/mrp_bom_location/tests/test_mrp_bom.py
odoo/addons/mrp_bom_location/views/mrp_view.xml
odoo/addons/mrp_bom_location/views/report_mrpbomstructure.xml
odoo_addon_mrp_bom_location-18.0.1.1.2.2.dist-info/METADATA
odoo_addon_mrp_bom_location-18.0.1.1.2.2.dist-info/WHEEL
odoo_addon_mrp_bom_location-18.0.1.1.2.2.dist-info/top_level.txt
odoo_addon_mrp_bom_location-18.0.1.1.2.2.dist-info/RECORD
