Metadata-Version: 2.1
Name: odoo-addon-mrp_bom_location
Version: 18.0.1.1.2.2
Requires-Python: >=3.10
Requires-Dist: odoo==18.0.*
Summary: Adds location field to Bill of Materials and its components.
Home-page: https://github.com/OCA/manufacture
License: LGPL-3
Author: ForgeFlow, Odoo Community Association (OCA)
Author-email: support@odoo-community.org
Classifier: Programming Language :: Python
Classifier: Framework :: Odoo
Classifier: Framework :: Odoo :: 18.0
Classifier: License :: OSI Approved :: GNU Lesser General Public License v3 (LGPLv3)
